uncertax/__init__.py
uncertax-0.0.1.dist-info/LICENSE
uncertax-0.0.1.dist-info/METADATA
uncertax-0.0.1.dist-info/WHEEL
uncertax-0.0.1.dist-info/top_level.txt
uncertax-0.0.1.dist-info/RECORD
