Metadata-Version: 2.1
Name: uncertax
Version: 0.0.1
Summary: A Python library for handling uncertainties in JAX
Home-page: https://github.com/yourusername/uncertax
Author: Your Name
Author-email: your.email@example.com
License: MIT
Classifier: Development Status :: 1 - Planning
Classifier: Intended Audience :: Developers
Classifier: License :: OSI Approved :: MIT License
Classifier: Programming Language :: Python :: 3
Classifier: Programming Language :: Python :: 3.7
Classifier: Programming Language :: Python :: 3.8
Classifier: Programming Language :: Python :: 3.9
License-File: LICENSE
